jvc_projector_remote/__init__.py
jvc_projector_remote/jvccommands.py
jvc_projector_remote/jvcprojector.py
jvc_projector_remote-0.2.3.dist-info/METADATA
jvc_projector_remote-0.2.3.dist-info/WHEEL
jvc_projector_remote-0.2.3.dist-info/licenses/LICENSE
jvc_projector_remote-0.2.3.dist-info/RECORD
