Metadata-Version: 2.1
Name: jvc_projector_remote
Version: 0.2.3
Summary: A package to control JVC projectors over IP
Project-URL: Homepage, https://github.com/bezmi/jvc_projector
Project-URL: Bug tracker, https://github.com/bezmi/jvc_projector/issues
Project-URL: Source archive, https://github.com/bezmi/jvc_projector/archive/2e2729725c6b97cc77fe6e0ab2a5514cec9c9c43.zip
Author: bezmi
License-File: LICENSE
Classifier: License :: OSI Approved :: MIT License
Classifier: Operating System :: OS Independent
Classifier: Programming Language :: Python :: 3
Requires-Python: >=3.8
